{
  "staves": [
    {
      "lines": [
        [
          [
            304, 
            350
          ], 
          [
            2332, 
            350
          ]
        ], 
        [
          [
            304, 
            363
          ], 
          [
            2332, 
            363
          ]
        ], 
        [
          [
            304, 
            376
          ], 
          [
            2332, 
            376
          ]
        ], 
        [
          [
            304, 
            390
          ], 
          [
            2332, 
            390
          ]
        ], 
        [
          [
            304, 
            403
          ], 
          [
            2332, 
            403
          ]
        ]
      ]
    }, 
    {
      "lines": [
        [
          [
            296, 
            544
          ], 
          [
            2331, 
            544
          ]
        ], 
        [
          [
            296, 
            556
          ], 
          [
            2331, 
            556
          ]
        ], 
        [
          [
            296, 
            570
          ], 
          [
            2331, 
            570
          ]
        ], 
        [
          [
            296, 
            584
          ], 
          [
            2331, 
            584
          ]
        ], 
        [
          [
            296, 
            597
          ], 
          [
            2331, 
            597
          ]
        ]
      ]
    }, 
    {
      "lines": [
        [
          [
            297, 
            749
          ], 
          [
            2330, 
            749
          ]
        ], 
        [
          [
            297, 
            763
          ], 
          [
            2330, 
            763
          ]
        ], 
        [
          [
            297, 
            776
          ], 
          [
            2330, 
            776
          ]
        ], 
        [
          [
            297, 
            790
          ], 
          [
            2330, 
            790
          ]
        ], 
        [
          [
            297, 
            803
          ], 
          [
            2330, 
            803
          ]
        ]
      ]
    }, 
    {
      "lines": [
        [
          [
            306, 
            951
          ], 
          [
            2329, 
            951
          ]
        ], 
        [
          [
            306, 
            965
          ], 
          [
            2329, 
            965
          ]
        ], 
        [
          [
            306, 
            978
          ], 
          [
            2329, 
            978
          ]
        ], 
        [
          [
            306, 
            990
          ], 
          [
            2329, 
            990
          ]
        ], 
        [
          [
            306, 
            1003
          ], 
          [
            2329, 
            1003
          ]
        ]
      ]
    }, 
    {
      "lines": [
        [
          [
            304, 
            1173
          ], 
          [
            2328, 
            1173
          ]
        ], 
        [
          [
            304, 
            1187
          ], 
          [
            2328, 
            1187
          ]
        ], 
        [
          [
            304, 
            1200
          ], 
          [
            2328, 
            1200
          ]
        ], 
        [
          [
            304, 
            1214
          ], 
          [
            2328, 
            1214
          ]
        ], 
        [
          [
            304, 
            1227
          ], 
          [
            2328, 
            1227
          ]
        ]
      ]
    }, 
    {
      "lines": [
        [
          [
            295, 
            1424
          ], 
          [
            2329, 
            1424
          ]
        ], 
        [
          [
            295, 
            1437
          ], 
          [
            2329, 
            1437
          ]
        ], 
        [
          [
            295, 
            1450
          ], 
          [
            2329, 
            1450
          ]
        ], 
        [
          [
            295, 
            1464
          ], 
          [
            2329, 
            1464
          ]
        ], 
        [
          [
            295, 
            1477
          ], 
          [
            2329, 
            1477
          ]
        ]
      ]
    }, 
    {
      "lines": [
        [
          [
            295, 
            1616
          ], 
          [
            2327, 
            1616
          ]
        ], 
        [
          [
            295, 
            1628
          ], 
          [
            2327, 
            1628
          ]
        ], 
        [
          [
            295, 
            1643
          ], 
          [
            2327, 
            1643
          ]
        ], 
        [
          [
            295, 
            1656
          ], 
          [
            2327, 
            1656
          ]
        ], 
        [
          [
            295, 
            1669
          ], 
          [
            2327, 
            1669
          ]
        ]
      ]
    }, 
    {
      "lines": [
        [
          [
            302, 
            1828
          ], 
          [
            2326, 
            1828
          ]
        ], 
        [
          [
            302, 
            1841
          ], 
          [
            2326, 
            1841
          ]
        ], 
        [
          [
            302, 
            1855
          ], 
          [
            2326, 
            1855
          ]
        ], 
        [
          [
            302, 
            1868
          ], 
          [
            2326, 
            1868
          ]
        ], 
        [
          [
            302, 
            1881
          ], 
          [
            2326, 
            1881
          ]
        ]
      ]
    }, 
    {
      "lines": [
        [
          [
            292, 
            2145
          ], 
          [
            2325, 
            2145
          ]
        ], 
        [
          [
            292, 
            2157
          ], 
          [
            2325, 
            2157
          ]
        ], 
        [
          [
            292, 
            2171
          ], 
          [
            2325, 
            2171
          ]
        ], 
        [
          [
            292, 
            2184
          ], 
          [
            2325, 
            2184
          ]
        ], 
        [
          [
            292, 
            2197
          ], 
          [
            2325, 
            2197
          ]
        ]
      ]
    }, 
    {
      "lines": [
        [
          [
            291, 
            2325
          ], 
          [
            2326, 
            2325
          ]
        ], 
        [
          [
            291, 
            2339
          ], 
          [
            2326, 
            2339
          ]
        ], 
        [
          [
            291, 
            2352
          ], 
          [
            2326, 
            2352
          ]
        ], 
        [
          [
            291, 
            2366
          ], 
          [
            2326, 
            2366
          ]
        ], 
        [
          [
            291, 
            2379
          ], 
          [
            2326, 
            2379
          ]
        ]
      ]
    }, 
    {
      "lines": [
        [
          [
            301, 
            2536
          ], 
          [
            2325, 
            2536
          ]
        ], 
        [
          [
            301, 
            2549
          ], 
          [
            2325, 
            2549
          ]
        ], 
        [
          [
            301, 
            2563
          ], 
          [
            2325, 
            2563
          ]
        ], 
        [
          [
            301, 
            2577
          ], 
          [
            2325, 
            2577
          ]
        ], 
        [
          [
            301, 
            2590
          ], 
          [
            2325, 
            2590
          ]
        ]
      ]
    }, 
    {
      "lines": [
        [
          [
            292, 
            2748
          ], 
          [
            2323, 
            2748
          ]
        ], 
        [
          [
            292, 
            2760
          ], 
          [
            2323, 
            2760
          ]
        ], 
        [
          [
            292, 
            2773
          ], 
          [
            2323, 
            2773
          ]
        ], 
        [
          [
            292, 
            2786
          ], 
          [
            2323, 
            2786
          ]
        ], 
        [
          [
            292, 
            2799
          ], 
          [
            2323, 
            2799
          ]
        ]
      ]
    }, 
    {
      "lines": [
        [
          [
            287, 
            2934
          ], 
          [
            2323, 
            2934
          ]
        ], 
        [
          [
            287, 
            2948
          ], 
          [
            2323, 
            2948
          ]
        ], 
        [
          [
            287, 
            2961
          ], 
          [
            2323, 
            2961
          ]
        ], 
        [
          [
            287, 
            2973
          ], 
          [
            2323, 
            2973
          ]
        ], 
        [
          [
            287, 
            2988
          ], 
          [
            2323, 
            2988
          ]
        ]
      ]
    }
  ]
}