{
  "measures": [
    {
      "bottom": 404,
      "end": 901,
      "start": 454,
      "system": 1,
      "top": 334
    },
    {
      "bottom": 531,
      "end": 901,
      "start": 454,
      "system": 1,
      "top": 462
    },
    {
      "bottom": 675,
      "end": 901,
      "start": 454,
      "system": 1,
      "top": 605
    },
    {
      "bottom": 805,
      "end": 901,
      "start": 454,
      "system": 1,
      "top": 735
    },
    {
      "bottom": 933,
      "end": 901,
      "start": 454,
      "system": 1,
      "top": 863
    },
    {
      "bottom": 1094,
      "end": 901,
      "start": 454,
      "system": 1,
      "top": 1025
    },
    {
      "bottom": 1221,
      "end": 901,
      "start": 454,
      "system": 1,
      "top": 1151
    },
    {
      "bottom": 1428,
      "end": 901,
      "start": 454,
      "system": 1,
      "top": 1358
    },
    {
      "bottom": 1593,
      "end": 901,
      "start": 454,
      "system": 1,
      "top": 1523
    },
    {
      "bottom": 1764,
      "end": 901,
      "start": 454,
      "system": 1,
      "top": 1695
    },
    {
      "bottom": 1892,
      "end": 901,
      "start": 454,
      "system": 1,
      "top": 1822
    },
    {
      "bottom": 2021,
      "end": 901,
      "start": 454,
      "system": 1,
      "top": 1951
    },
    {
      "bottom": 2162,
      "end": 901,
      "start": 454,
      "system": 1,
      "top": 2092
    },
    {
      "bottom": 2308,
      "end": 901,
      "start": 454,
      "system": 1,
      "top": 2238
    },
    {
      "bottom": 2477,
      "end": 901,
      "start": 454,
      "system": 1,
      "top": 2408
    },
    {
      "bottom": 2602,
      "end": 901,
      "start": 454,
      "system": 1,
      "top": 2533
    },
    {
      "bottom": 2749,
      "end": 901,
      "start": 454,
      "system": 1,
      "top": 2679
    },
    {
      "bottom": 2894,
      "end": 901,
      "start": 454,
      "system": 1,
      "top": 2824
    },
    {
      "bottom": 3060,
      "end": 901,
      "start": 454,
      "system": 1,
      "top": 2990
    },
    {
      "bottom": 3206,
      "end": 901,
      "start": 454,
      "system": 1,
      "top": 3136
    },
    {
      "bottom": 3311,
      "end": 901,
      "start": 454,
      "system": 1,
      "top": 3311
    },
    {
      "bottom": 3404,
      "end": 901,
      "start": 454,
      "system": 1,
      "top": 3404
    },
    {
      "bottom": 3614,
      "end": 901,
      "start": 454,
      "system": 1,
      "top": 3544
    },
    {
      "bottom": 3760,
      "end": 901,
      "start": 454,
      "system": 1,
      "top": 3690
    },
    {
      "bottom": 4055,
      "end": 901,
      "start": 454,
      "system": 1,
      "top": 3985
    },
    {
      "bottom": 4186,
      "end": 901,
      "start": 454,
      "system": 1,
      "top": 4116
    },
    {
      "bottom": 4321,
      "end": 901,
      "start": 454,
      "system": 1,
      "top": 4251
    },
    {
      "bottom": 4470,
      "end": 901,
      "start": 454,
      "system": 1,
      "top": 4400
    },
    {
      "bottom": 4641,
      "end": 901,
      "start": 454,
      "system": 1,
      "top": 4570
    },
    {
      "bottom": 404,
      "end": 1289,
      "start": 901,
      "system": 1,
      "top": 334
    },
    {
      "bottom": 531,
      "end": 1289,
      "start": 901,
      "system": 1,
      "top": 462
    },
    {
      "bottom": 675,
      "end": 1289,
      "start": 901,
      "system": 1,
      "top": 605
    },
    {
      "bottom": 805,
      "end": 1289,
      "start": 901,
      "system": 1,
      "top": 735
    },
    {
      "bottom": 933,
      "end": 1289,
      "start": 901,
      "system": 1,
      "top": 863
    },
    {
      "bottom": 1094,
      "end": 1289,
      "start": 901,
      "system": 1,
      "top": 1025
    },
    {
      "bottom": 1221,
      "end": 1289,
      "start": 901,
      "system": 1,
      "top": 1151
    },
    {
      "bottom": 1428,
      "end": 1289,
      "start": 901,
      "system": 1,
      "top": 1358
    },
    {
      "bottom": 1593,
      "end": 1289,
      "start": 901,
      "system": 1,
      "top": 1523
    },
    {
      "bottom": 1764,
      "end": 1289,
      "start": 901,
      "system": 1,
      "top": 1695
    },
    {
      "bottom": 1892,
      "end": 1289,
      "start": 901,
      "system": 1,
      "top": 1822
    },
    {
      "bottom": 2021,
      "end": 1289,
      "start": 901,
      "system": 1,
      "top": 1951
    },
    {
      "bottom": 2162,
      "end": 1289,
      "start": 901,
      "system": 1,
      "top": 2092
    },
    {
      "bottom": 2308,
      "end": 1289,
      "start": 901,
      "system": 1,
      "top": 2238
    },
    {
      "bottom": 2477,
      "end": 1289,
      "start": 901,
      "system": 1,
      "top": 2408
    },
    {
      "bottom": 2602,
      "end": 1289,
      "start": 901,
      "system": 1,
      "top": 2533
    },
    {
      "bottom": 2749,
      "end": 1289,
      "start": 901,
      "system": 1,
      "top": 2679
    },
    {
      "bottom": 2894,
      "end": 1289,
      "start": 901,
      "system": 1,
      "top": 2824
    },
    {
      "bottom": 3060,
      "end": 1289,
      "start": 901,
      "system": 1,
      "top": 2990
    },
    {
      "bottom": 3206,
      "end": 1289,
      "start": 901,
      "system": 1,
      "top": 3136
    },
    {
      "bottom": 3311,
      "end": 1289,
      "start": 901,
      "system": 1,
      "top": 3311
    },
    {
      "bottom": 3404,
      "end": 1289,
      "start": 901,
      "system": 1,
      "top": 3404
    },
    {
      "bottom": 3614,
      "end": 1289,
      "start": 901,
      "system": 1,
      "top": 3544
    },
    {
      "bottom": 3760,
      "end": 1289,
      "start": 901,
      "system": 1,
      "top": 3690
    },
    {
      "bottom": 4055,
      "end": 1289,
      "start": 901,
      "system": 1,
      "top": 3985
    },
    {
      "bottom": 4186,
      "end": 1289,
      "start": 901,
      "system": 1,
      "top": 4116
    },
    {
      "bottom": 4321,
      "end": 1289,
      "start": 901,
      "system": 1,
      "top": 4251
    },
    {
      "bottom": 4470,
      "end": 1289,
      "start": 901,
      "system": 1,
      "top": 4400
    },
    {
      "bottom": 4641,
      "end": 1289,
      "start": 901,
      "system": 1,
      "top": 4570
    },
    {
      "bottom": 404,
      "end": 1701,
      "start": 1289,
      "system": 1,
      "top": 334
    },
    {
      "bottom": 531,
      "end": 1701,
      "start": 1289,
      "system": 1,
      "top": 462
    },
    {
      "bottom": 675,
      "end": 1701,
      "start": 1289,
      "system": 1,
      "top": 605
    },
    {
      "bottom": 805,
      "end": 1701,
      "start": 1289,
      "system": 1,
      "top": 735
    },
    {
      "bottom": 933,
      "end": 1701,
      "start": 1289,
      "system": 1,
      "top": 863
    },
    {
      "bottom": 1094,
      "end": 1701,
      "start": 1289,
      "system": 1,
      "top": 1025
    },
    {
      "bottom": 1221,
      "end": 1701,
      "start": 1289,
      "system": 1,
      "top": 1151
    },
    {
      "bottom": 1428,
      "end": 1701,
      "start": 1289,
      "system": 1,
      "top": 1358
    },
    {
      "bottom": 1593,
      "end": 1701,
      "start": 1289,
      "system": 1,
      "top": 1523
    },
    {
      "bottom": 1764,
      "end": 1701,
      "start": 1289,
      "system": 1,
      "top": 1695
    },
    {
      "bottom": 1892,
      "end": 1701,
      "start": 1289,
      "system": 1,
      "top": 1822
    },
    {
      "bottom": 2021,
      "end": 1701,
      "start": 1289,
      "system": 1,
      "top": 1951
    },
    {
      "bottom": 2162,
      "end": 1701,
      "start": 1289,
      "system": 1,
      "top": 2092
    },
    {
      "bottom": 2308,
      "end": 1701,
      "start": 1289,
      "system": 1,
      "top": 2238
    },
    {
      "bottom": 2477,
      "end": 1701,
      "start": 1289,
      "system": 1,
      "top": 2408
    },
    {
      "bottom": 2602,
      "end": 1701,
      "start": 1289,
      "system": 1,
      "top": 2533
    },
    {
      "bottom": 2749,
      "end": 1701,
      "start": 1289,
      "system": 1,
      "top": 2679
    },
    {
      "bottom": 2894,
      "end": 1701,
      "start": 1289,
      "system": 1,
      "top": 2824
    },
    {
      "bottom": 3060,
      "end": 1701,
      "start": 1289,
      "system": 1,
      "top": 2990
    },
    {
      "bottom": 3206,
      "end": 1701,
      "start": 1289,
      "system": 1,
      "top": 3136
    },
    {
      "bottom": 3311,
      "end": 1701,
      "start": 1289,
      "system": 1,
      "top": 3311
    },
    {
      "bottom": 3404,
      "end": 1701,
      "start": 1289,
      "system": 1,
      "top": 3404
    },
    {
      "bottom": 3614,
      "end": 1701,
      "start": 1289,
      "system": 1,
      "top": 3544
    },
    {
      "bottom": 3760,
      "end": 1701,
      "start": 1289,
      "system": 1,
      "top": 3690
    },
    {
      "bottom": 4055,
      "end": 1701,
      "start": 1289,
      "system": 1,
      "top": 3985
    },
    {
      "bottom": 4186,
      "end": 1701,
      "start": 1289,
      "system": 1,
      "top": 4116
    },
    {
      "bottom": 4321,
      "end": 1701,
      "start": 1289,
      "system": 1,
      "top": 4251
    },
    {
      "bottom": 4470,
      "end": 1701,
      "start": 1289,
      "system": 1,
      "top": 4400
    },
    {
      "bottom": 4641,
      "end": 1701,
      "start": 1289,
      "system": 1,
      "top": 4570
    },
    {
      "bottom": 404,
      "end": 2039,
      "start": 1701,
      "system": 1,
      "top": 334
    },
    {
      "bottom": 531,
      "end": 2039,
      "start": 1701,
      "system": 1,
      "top": 462
    },
    {
      "bottom": 675,
      "end": 2039,
      "start": 1701,
      "system": 1,
      "top": 605
    },
    {
      "bottom": 805,
      "end": 2039,
      "start": 1701,
      "system": 1,
      "top": 735
    },
    {
      "bottom": 933,
      "end": 2039,
      "start": 1701,
      "system": 1,
      "top": 863
    },
    {
      "bottom": 1094,
      "end": 2039,
      "start": 1701,
      "system": 1,
      "top": 1025
    },
    {
      "bottom": 1221,
      "end": 2039,
      "start": 1701,
      "system": 1,
      "top": 1151
    },
    {
      "bottom": 1428,
      "end": 2039,
      "start": 1701,
      "system": 1,
      "top": 1358
    },
    {
      "bottom": 1593,
      "end": 2039,
      "start": 1701,
      "system": 1,
      "top": 1523
    },
    {
      "bottom": 1764,
      "end": 2039,
      "start": 1701,
      "system": 1,
      "top": 1695
    },
    {
      "bottom": 1892,
      "end": 2039,
      "start": 1701,
      "system": 1,
      "top": 1822
    },
    {
      "bottom": 2021,
      "end": 2039,
      "start": 1701,
      "system": 1,
      "top": 1951
    },
    {
      "bottom": 2162,
      "end": 2039,
      "start": 1701,
      "system": 1,
      "top": 2092
    },
    {
      "bottom": 2308,
      "end": 2039,
      "start": 1701,
      "system": 1,
      "top": 2238
    },
    {
      "bottom": 2477,
      "end": 2039,
      "start": 1701,
      "system": 1,
      "top": 2408
    },
    {
      "bottom": 2602,
      "end": 2039,
      "start": 1701,
      "system": 1,
      "top": 2533
    },
    {
      "bottom": 2749,
      "end": 2039,
      "start": 1701,
      "system": 1,
      "top": 2679
    },
    {
      "bottom": 2894,
      "end": 2039,
      "start": 1701,
      "system": 1,
      "top": 2824
    },
    {
      "bottom": 3060,
      "end": 2039,
      "start": 1701,
      "system": 1,
      "top": 2990
    },
    {
      "bottom": 3206,
      "end": 2039,
      "start": 1701,
      "system": 1,
      "top": 3136
    },
    {
      "bottom": 3311,
      "end": 2039,
      "start": 1701,
      "system": 1,
      "top": 3311
    },
    {
      "bottom": 3404,
      "end": 2039,
      "start": 1701,
      "system": 1,
      "top": 3404
    },
    {
      "bottom": 3614,
      "end": 2039,
      "start": 1701,
      "system": 1,
      "top": 3544
    },
    {
      "bottom": 3760,
      "end": 2039,
      "start": 1701,
      "system": 1,
      "top": 3690
    },
    {
      "bottom": 4055,
      "end": 2039,
      "start": 1701,
      "system": 1,
      "top": 3985
    },
    {
      "bottom": 4186,
      "end": 2039,
      "start": 1701,
      "system": 1,
      "top": 4116
    },
    {
      "bottom": 4321,
      "end": 2039,
      "start": 1701,
      "system": 1,
      "top": 4251
    },
    {
      "bottom": 4470,
      "end": 2039,
      "start": 1701,
      "system": 1,
      "top": 4400
    },
    {
      "bottom": 4641,
      "end": 2039,
      "start": 1701,
      "system": 1,
      "top": 4570
    },
    {
      "bottom": 404,
      "end": 2412,
      "start": 2039,
      "system": 1,
      "top": 334
    },
    {
      "bottom": 531,
      "end": 2412,
      "start": 2039,
      "system": 1,
      "top": 462
    },
    {
      "bottom": 675,
      "end": 2412,
      "start": 2039,
      "system": 1,
      "top": 605
    },
    {
      "bottom": 805,
      "end": 2412,
      "start": 2039,
      "system": 1,
      "top": 735
    },
    {
      "bottom": 933,
      "end": 2412,
      "start": 2039,
      "system": 1,
      "top": 863
    },
    {
      "bottom": 1094,
      "end": 2412,
      "start": 2039,
      "system": 1,
      "top": 1025
    },
    {
      "bottom": 1221,
      "end": 2412,
      "start": 2039,
      "system": 1,
      "top": 1151
    },
    {
      "bottom": 1428,
      "end": 2412,
      "start": 2039,
      "system": 1,
      "top": 1358
    },
    {
      "bottom": 1593,
      "end": 2412,
      "start": 2039,
      "system": 1,
      "top": 1523
    },
    {
      "bottom": 1764,
      "end": 2412,
      "start": 2039,
      "system": 1,
      "top": 1695
    },
    {
      "bottom": 1892,
      "end": 2412,
      "start": 2039,
      "system": 1,
      "top": 1822
    },
    {
      "bottom": 2021,
      "end": 2412,
      "start": 2039,
      "system": 1,
      "top": 1951
    },
    {
      "bottom": 2162,
      "end": 2412,
      "start": 2039,
      "system": 1,
      "top": 2092
    },
    {
      "bottom": 2308,
      "end": 2412,
      "start": 2039,
      "system": 1,
      "top": 2238
    },
    {
      "bottom": 2477,
      "end": 2412,
      "start": 2039,
      "system": 1,
      "top": 2408
    },
    {
      "bottom": 2602,
      "end": 2412,
      "start": 2039,
      "system": 1,
      "top": 2533
    },
    {
      "bottom": 2749,
      "end": 2412,
      "start": 2039,
      "system": 1,
      "top": 2679
    },
    {
      "bottom": 2894,
      "end": 2412,
      "start": 2039,
      "system": 1,
      "top": 2824
    },
    {
      "bottom": 3060,
      "end": 2412,
      "start": 2039,
      "system": 1,
      "top": 2990
    },
    {
      "bottom": 3206,
      "end": 2412,
      "start": 2039,
      "system": 1,
      "top": 3136
    },
    {
      "bottom": 3311,
      "end": 2412,
      "start": 2039,
      "system": 1,
      "top": 3311
    },
    {
      "bottom": 3404,
      "end": 2412,
      "start": 2039,
      "system": 1,
      "top": 3404
    },
    {
      "bottom": 3614,
      "end": 2412,
      "start": 2039,
      "system": 1,
      "top": 3544
    },
    {
      "bottom": 3760,
      "end": 2412,
      "start": 2039,
      "system": 1,
      "top": 3690
    },
    {
      "bottom": 4055,
      "end": 2412,
      "start": 2039,
      "system": 1,
      "top": 3985
    },
    {
      "bottom": 4186,
      "end": 2412,
      "start": 2039,
      "system": 1,
      "top": 4116
    },
    {
      "bottom": 4321,
      "end": 2412,
      "start": 2039,
      "system": 1,
      "top": 4251
    },
    {
      "bottom": 4470,
      "end": 2412,
      "start": 2039,
      "system": 1,
      "top": 4400
    },
    {
      "bottom": 4641,
      "end": 2412,
      "start": 2039,
      "system": 1,
      "top": 4570
    },
    {
      "bottom": 404,
      "end": 2782,
      "start": 2412,
      "system": 1,
      "top": 334
    },
    {
      "bottom": 531,
      "end": 2782,
      "start": 2412,
      "system": 1,
      "top": 462
    },
    {
      "bottom": 675,
      "end": 2782,
      "start": 2412,
      "system": 1,
      "top": 605
    },
    {
      "bottom": 805,
      "end": 2782,
      "start": 2412,
      "system": 1,
      "top": 735
    },
    {
      "bottom": 933,
      "end": 2782,
      "start": 2412,
      "system": 1,
      "top": 863
    },
    {
      "bottom": 1094,
      "end": 2782,
      "start": 2412,
      "system": 1,
      "top": 1025
    },
    {
      "bottom": 1221,
      "end": 2782,
      "start": 2412,
      "system": 1,
      "top": 1151
    },
    {
      "bottom": 1428,
      "end": 2782,
      "start": 2412,
      "system": 1,
      "top": 1358
    },
    {
      "bottom": 1593,
      "end": 2782,
      "start": 2412,
      "system": 1,
      "top": 1523
    },
    {
      "bottom": 1764,
      "end": 2782,
      "start": 2412,
      "system": 1,
      "top": 1695
    },
    {
      "bottom": 1892,
      "end": 2782,
      "start": 2412,
      "system": 1,
      "top": 1822
    },
    {
      "bottom": 2021,
      "end": 2782,
      "start": 2412,
      "system": 1,
      "top": 1951
    },
    {
      "bottom": 2162,
      "end": 2782,
      "start": 2412,
      "system": 1,
      "top": 2092
    },
    {
      "bottom": 2308,
      "end": 2782,
      "start": 2412,
      "system": 1,
      "top": 2238
    },
    {
      "bottom": 2477,
      "end": 2782,
      "start": 2412,
      "system": 1,
      "top": 2408
    },
    {
      "bottom": 2602,
      "end": 2782,
      "start": 2412,
      "system": 1,
      "top": 2533
    },
    {
      "bottom": 2749,
      "end": 2782,
      "start": 2412,
      "system": 1,
      "top": 2679
    },
    {
      "bottom": 2894,
      "end": 2782,
      "start": 2412,
      "system": 1,
      "top": 2824
    },
    {
      "bottom": 3060,
      "end": 2782,
      "start": 2412,
      "system": 1,
      "top": 2990
    },
    {
      "bottom": 3206,
      "end": 2782,
      "start": 2412,
      "system": 1,
      "top": 3136
    },
    {
      "bottom": 3311,
      "end": 2782,
      "start": 2412,
      "system": 1,
      "top": 3311
    },
    {
      "bottom": 3404,
      "end": 2782,
      "start": 2412,
      "system": 1,
      "top": 3404
    },
    {
      "bottom": 3614,
      "end": 2782,
      "start": 2412,
      "system": 1,
      "top": 3544
    },
    {
      "bottom": 3760,
      "end": 2782,
      "start": 2412,
      "system": 1,
      "top": 3690
    },
    {
      "bottom": 4055,
      "end": 2782,
      "start": 2412,
      "system": 1,
      "top": 3985
    },
    {
      "bottom": 4186,
      "end": 2782,
      "start": 2412,
      "system": 1,
      "top": 4116
    },
    {
      "bottom": 4321,
      "end": 2782,
      "start": 2412,
      "system": 1,
      "top": 4251
    },
    {
      "bottom": 4470,
      "end": 2782,
      "start": 2412,
      "system": 1,
      "top": 4400
    },
    {
      "bottom": 4641,
      "end": 2782,
      "start": 2412,
      "system": 1,
      "top": 4570
    },
    {
      "bottom": 404,
      "end": 3108,
      "start": 2782,
      "system": 1,
      "top": 334
    },
    {
      "bottom": 531,
      "end": 3108,
      "start": 2782,
      "system": 1,
      "top": 462
    },
    {
      "bottom": 675,
      "end": 3108,
      "start": 2782,
      "system": 1,
      "top": 605
    },
    {
      "bottom": 805,
      "end": 3108,
      "start": 2782,
      "system": 1,
      "top": 735
    },
    {
      "bottom": 933,
      "end": 3108,
      "start": 2782,
      "system": 1,
      "top": 863
    },
    {
      "bottom": 1094,
      "end": 3108,
      "start": 2782,
      "system": 1,
      "top": 1025
    },
    {
      "bottom": 1221,
      "end": 3108,
      "start": 2782,
      "system": 1,
      "top": 1151
    },
    {
      "bottom": 1428,
      "end": 3108,
      "start": 2782,
      "system": 1,
      "top": 1358
    },
    {
      "bottom": 1593,
      "end": 3108,
      "start": 2782,
      "system": 1,
      "top": 1523
    },
    {
      "bottom": 1764,
      "end": 3108,
      "start": 2782,
      "system": 1,
      "top": 1695
    },
    {
      "bottom": 1892,
      "end": 3108,
      "start": 2782,
      "system": 1,
      "top": 1822
    },
    {
      "bottom": 2021,
      "end": 3108,
      "start": 2782,
      "system": 1,
      "top": 1951
    },
    {
      "bottom": 2162,
      "end": 3108,
      "start": 2782,
      "system": 1,
      "top": 2092
    },
    {
      "bottom": 2308,
      "end": 3108,
      "start": 2782,
      "system": 1,
      "top": 2238
    },
    {
      "bottom": 2477,
      "end": 3108,
      "start": 2782,
      "system": 1,
      "top": 2408
    },
    {
      "bottom": 2602,
      "end": 3108,
      "start": 2782,
      "system": 1,
      "top": 2533
    },
    {
      "bottom": 2749,
      "end": 3108,
      "start": 2782,
      "system": 1,
      "top": 2679
    },
    {
      "bottom": 2894,
      "end": 3108,
      "start": 2782,
      "system": 1,
      "top": 2824
    },
    {
      "bottom": 3060,
      "end": 3108,
      "start": 2782,
      "system": 1,
      "top": 2990
    },
    {
      "bottom": 3206,
      "end": 3108,
      "start": 2782,
      "system": 1,
      "top": 3136
    },
    {
      "bottom": 3311,
      "end": 3108,
      "start": 2782,
      "system": 1,
      "top": 3311
    },
    {
      "bottom": 3404,
      "end": 3108,
      "start": 2782,
      "system": 1,
      "top": 3404
    },
    {
      "bottom": 3614,
      "end": 3108,
      "start": 2782,
      "system": 1,
      "top": 3544
    },
    {
      "bottom": 3760,
      "end": 3108,
      "start": 2782,
      "system": 1,
      "top": 3690
    },
    {
      "bottom": 4055,
      "end": 3108,
      "start": 2782,
      "system": 1,
      "top": 3985
    },
    {
      "bottom": 4186,
      "end": 3108,
      "start": 2782,
      "system": 1,
      "top": 4116
    },
    {
      "bottom": 4321,
      "end": 3108,
      "start": 2782,
      "system": 1,
      "top": 4251
    },
    {
      "bottom": 4470,
      "end": 3108,
      "start": 2782,
      "system": 1,
      "top": 4400
    },
    {
      "bottom": 4641,
      "end": 3108,
      "start": 2782,
      "system": 1,
      "top": 4570
    },
    {
      "bottom": 404,
      "end": 3512,
      "start": 3108,
      "system": 1,
      "top": 334
    },
    {
      "bottom": 531,
      "end": 3512,
      "start": 3108,
      "system": 1,
      "top": 462
    },
    {
      "bottom": 675,
      "end": 3512,
      "start": 3108,
      "system": 1,
      "top": 605
    },
    {
      "bottom": 805,
      "end": 3512,
      "start": 3108,
      "system": 1,
      "top": 735
    },
    {
      "bottom": 933,
      "end": 3512,
      "start": 3108,
      "system": 1,
      "top": 863
    },
    {
      "bottom": 1094,
      "end": 3512,
      "start": 3108,
      "system": 1,
      "top": 1025
    },
    {
      "bottom": 1221,
      "end": 3512,
      "start": 3108,
      "system": 1,
      "top": 1151
    },
    {
      "bottom": 1428,
      "end": 3512,
      "start": 3108,
      "system": 1,
      "top": 1358
    },
    {
      "bottom": 1593,
      "end": 3512,
      "start": 3108,
      "system": 1,
      "top": 1523
    },
    {
      "bottom": 1764,
      "end": 3512,
      "start": 3108,
      "system": 1,
      "top": 1695
    },
    {
      "bottom": 1892,
      "end": 3512,
      "start": 3108,
      "system": 1,
      "top": 1822
    },
    {
      "bottom": 2021,
      "end": 3512,
      "start": 3108,
      "system": 1,
      "top": 1951
    },
    {
      "bottom": 2162,
      "end": 3512,
      "start": 3108,
      "system": 1,
      "top": 2092
    },
    {
      "bottom": 2308,
      "end": 3512,
      "start": 3108,
      "system": 1,
      "top": 2238
    },
    {
      "bottom": 2477,
      "end": 3512,
      "start": 3108,
      "system": 1,
      "top": 2408
    },
    {
      "bottom": 2602,
      "end": 3512,
      "start": 3108,
      "system": 1,
      "top": 2533
    },
    {
      "bottom": 2749,
      "end": 3512,
      "start": 3108,
      "system": 1,
      "top": 2679
    },
    {
      "bottom": 2894,
      "end": 3512,
      "start": 3108,
      "system": 1,
      "top": 2824
    },
    {
      "bottom": 3060,
      "end": 3512,
      "start": 3108,
      "system": 1,
      "top": 2990
    },
    {
      "bottom": 3206,
      "end": 3512,
      "start": 3108,
      "system": 1,
      "top": 3136
    },
    {
      "bottom": 3311,
      "end": 3512,
      "start": 3108,
      "system": 1,
      "top": 3311
    },
    {
      "bottom": 3404,
      "end": 3512,
      "start": 3108,
      "system": 1,
      "top": 3404
    },
    {
      "bottom": 3614,
      "end": 3512,
      "start": 3108,
      "system": 1,
      "top": 3544
    },
    {
      "bottom": 3760,
      "end": 3512,
      "start": 3108,
      "system": 1,
      "top": 3690
    },
    {
      "bottom": 4055,
      "end": 3512,
      "start": 3108,
      "system": 1,
      "top": 3985
    },
    {
      "bottom": 4186,
      "end": 3512,
      "start": 3108,
      "system": 1,
      "top": 4116
    },
    {
      "bottom": 4321,
      "end": 3512,
      "start": 3108,
      "system": 1,
      "top": 4251
    },
    {
      "bottom": 4470,
      "end": 3512,
      "start": 3108,
      "system": 1,
      "top": 4400
    },
    {
      "bottom": 4641,
      "end": 3512,
      "start": 3108,
      "system": 1,
      "top": 4570
    }
  ]
}